<?xml version="1.0"?>
<!--<!DOCTYPE metadata SYSTEM "http://www.esri.com/metadata/esriprof80.dtd">-->
<metadata xml:lang="en"><Esri><MetaID>{1592B784-0E83-471F-B891-D097880A9BB8}</MetaID><CreaDate>20060817</CreaDate><CreaTime>15203800</CreaTime><SyncOnce>FALSE</SyncOnce><DataProperties><lineage><Process Name="Merge_1" ToolSource="C:\Program Files\ArcGIS\ArcToolbox\Toolboxes\Data Management Tools.tbx\Merge" Date="20060817" Time="152038">Merge Connecticut_Hydrography;NYS_Hydrography;water_LULC Y:\LLAB\NPCA-gateway\00_GIS\XDRIVE\US_Regional\NPS_Gateway_Region\Gateway\water_tristate.shp "HYPOLY_COD HYPOLY_COD true false false 10 Double 0 10 ,First,#,Connecticut_Hydrography,HYPOLY_COD,-1,-1;HYDRO_POLY HYDRO_POLY true false false 50 Text 0 0 ,First,#,Connecticut_Hydrography,HYDRO_POLY,-1,-1;AV_LEGEND AV_LEGEND true false false 20 Text 0 0 ,First,#,Connecticut_Hydrography,AV_LEGEND,-1,-1;IMS_LEGEND IMS_LEGEND true false false 20 Text 0 0 ,First,#,Connecticut_Hydrography,IMS_LEGEND,-1,-1;COASTP_COD COASTP_COD true false false 1 Short 0 1 ,First,#,Connecticut_Hydrography,COASTP_COD,-1,-1;COAST_POLY COAST_POLY true false false 30 Text 0 0 ,First,#,Connecticut_Hydrography,COAST_POLY,-1,-1;NAMEDP_COD NAMEDP_COD true false false 1 Short 0 1 ,First,#,Connecticut_Hydrography,NAMEDP_COD,-1,-1;NAMED_POLY NAMED_POLY true false false 40 Text 0 0 ,First,#,Connecticut_Hydrography,NAMED_POLY,-1,-1;SCALELEVEL SCALELEVEL true false false 1 Short 0 1 ,First,#,Connecticut_Hydrography,SCALELEVEL,-1,-1;STREAM_NO STREAM_NO true false false 5 Long 0 5 ,First,#,Connecticut_Hydrography,STREAM_NO,-1,-1;STREAM STREAM true false false 40 Text 0 0 ,First,#,Connecticut_Hydrography,STREAM,-1,-1;LAKE_NO LAKE_NO true false false 5 Long 0 5 ,First,#,Connecticut_Hydrography,LAKE_NO,-1,-1;LAKE LAKE true false false 40 Text 0 0 ,First,#,Connecticut_Hydrography,LAKE,-1,-1;BAY_NO BAY_NO true false false 5 Long 0 5 ,First,#,Connecticut_Hydrography,BAY_NO,-1,-1;BAY BAY true false false 40 Text 0 0 ,First,#,Connecticut_Hydrography,BAY,-1,-1;HARBOR_NO HARBOR_NO true false false 5 Long 0 5 ,First,#,Connecticut_Hydrography,HARBOR_NO,-1,-1;HARBOR HARBOR true false false 40 Text 0 0 ,First,#,Connecticut_Hydrography,HARBOR,-1,-1;SOUND_NO SOUND_NO true false false 5 Long 0 5 ,First,#,Connecticut_Hydrography,SOUND_NO,-1,-1;SOUND SOUND true false false 30 Text 0 0 ,First,#,Connecticut_Hydrography,SOUND,-1,-1;ACREAGE ACREAGE true false false 13 Float 11 12 ,First,#,Connecticut_Hydrography,ACREAGE,-1,-1;NAME NAME true false false 40 Text 0 0 ,First,#,NYS_Hydrography,NAME,-1,-1;FCC FCC true false false 3 Text 0 0 ,First,#,NYS_Hydrography,FCC,-1,-1;BUS_FID_Le BUS_FID_Le true false false 19 Double 11 18 ,First,#,NYS_Hydrography,BUS_FID_Le,-1,-1;BUS_FID_Ar BUS_FID_Ar true false false 19 Double 11 18 ,First,#,NYS_Hydrography,BUS_FID_Ar,-1,-1;AREA AREA true false false 19 Double 5 18 ,First,#,water_LULC,AREA,-1,-1;PERIMETER PERIMETER true false false 19 Double 5 18 ,First,#,water_LULC,PERIMETER,-1,-1;W07LU95_ W07LU95_ true false false 11 Double 0 11 ,First,#,water_LULC,W07LU95_,-1,-1;W07LU95_ID W07LU95_ID true false false 11 Double 0 11 ,First,#,water_LULC,W07LU95_ID,-1,-1;STATUS STATUS true false false 16 Text 0 0 ,First,#,water_LULC,STATUS,-1,-1;APPROVAL APPROVAL true false false 8 Text 0 0 ,First,#,water_LULC,APPROVAL,-1,-1;ACRES ACRES true false false 15 Double 3 14 ,First,#,water_LULC,ACRES,-1,-1;LU95 LU95 true false false 4 Short 0 4 ,First,#,water_LULC,LU95,-1,-1;LABEL95 LABEL95 true false false 65 Text 0 0 ,First,#,water_LULC,LABEL95,-1,-1;TYPE95 TYPE95 true false false 15 Text 0 0 ,First,#,water_LULC,TYPE95,-1,-1;IS_ IS_ true false false 4 Short 0 4 ,First,#,water_LULC,IS_,-1,-1;ISACRES ISACRES true false false 15 Double 3 14 ,First,#,water_LULC,ISACRES,-1,-1;CHANGE86 CHANGE86 true false false 2 Short 0 2 ,First,#,water_LULC,CHANGE86,-1,-1;LU86 LU86 true false false 4 Short 0 4 ,First,#,water_LULC,LU86,-1,-1;LABEL86 LABEL86 true false false 65 Text 0 0 ,First,#,water_LULC,LABEL86,-1,-1;TYPE86 TYPE86 true false false 15 Text 0 0 ,First,#,water_LULC,TYPE86,-1,-1;CLASS CLASS true false false 6 Long 0 6 ,First,#,water_LULC,CLASS,-1,-1;COWARDIN COWARDIN true false false 14 Text 0 0 ,First,#,water_LULC,COWARDIN,-1,-1;W20LU95_ W20LU95_ true false false 11 Double 0 11 ,First,#,water_LULC,W20LU95_,-1,-1;W20LU95_ID W20LU95_ID true false false 11 Double 0 11 ,First,#,water_LULC,W20LU95_ID,-1,-1;IS1 IS1 true false false 4 Short 0 4 ,First,#,water_LULC,IS1,-1,-1;W13LU95_ W13LU95_ true false false 11 Double 0 11 ,First,#,water_LULC,W13LU95_,-1,-1;W13LU95_ID W13LU95_ID true false false 11 Double 0 11 ,First,#,water_LULC,W13LU95_ID,-1,-1;IS1_1 IS1_1 true false false 4 Short 0 4 ,First,#,water_LULC,IS1_1,-1,-1;W16LU95_ W16LU95_ true false false 11 Double 0 11 ,First,#,water_LULC,W16LU95_,-1,-1;W16LU95_ID W16LU95_ID true false false 11 Double 0 11 ,First,#,water_LULC,W16LU95_ID,-1,-1;IS1_12 IS1_12 true false false 4 Short 0 4 ,First,#,water_LULC,IS1_12,-1,-1;W11LU95_ W11LU95_ true false false 11 Double 0 11 ,First,#,water_LULC,W11LU95_,-1,-1;W11LU95_ID W11LU95_ID true false false 11 Double 0 11 ,First,#,water_LULC,W11LU95_ID,-1,-1;IS1_12_13 IS1_12_13 true false false 4 Short 0 4 ,First,#,water_LULC,IS1_12_13,-1,-1;W15LU95_ W15LU95_ true false false 11 Double 0 11 ,First,#,water_LULC,W15LU95_,-1,-1;W15LU95_ID W15LU95_ID true false false 11 Double 0 11 ,First,#,water_LULC,W15LU95_ID,-1,-1;IS1_12__14 IS1_12__14 true false false 4 Short 0 4 ,First,#,water_LULC,IS1_12__14,-1,-1;W05LU95_ W05LU95_ true false false 11 Double 0 11 ,First,#,water_LULC,W05LU95_,-1,-1;W05LU95_ID W05LU95_ID true false false 11 Double 0 11 ,First,#,water_LULC,W05LU95_ID,-1,-1;IS1_12__15 IS1_12__15 true false false 4 Short 0 4 ,First,#,water_LULC,IS1_12__15,-1,-1;W18LU95_ W18LU95_ true false false 11 Double 0 11 ,First,#,water_LULC,W18LU95_,-1,-1;W18LU95_ID W18LU95_ID true false false 11 Double 0 11 ,First,#,water_LULC,W18LU95_ID,-1,-1;IS1_12__16 IS1_12__16 true false false 4 Short 0 4 ,First,#,water_LULC,IS1_12__16,-1,-1;W04LU95_ W04LU95_ true false false 11 Double 0 11 ,First,#,water_LULC,W04LU95_,-1,-1;W04LU95_ID W04LU95_ID true false false 11 Double 0 11 ,First,#,water_LULC,W04LU95_ID,-1,-1;IS1_12__17 IS1_12__17 true false false 4 Short 0 4 ,First,#,water_LULC,IS1_12__17,-1,-1;W09LU95_ W09LU95_ true false false 11 Double 0 11 ,First,#,water_LULC,W09LU95_,-1,-1;W09LU95_ID W09LU95_ID true false false 11 Double 0 11 ,First,#,water_LULC,W09LU95_ID,-1,-1;IS1_12__18 IS1_12__18 true false false 4 Short 0 4 ,First,#,water_LULC,IS1_12__18,-1,-1;W17LU95_ W17LU95_ true false false 11 Double 0 11 ,First,#,water_LULC,W17LU95_,-1,-1;W17LU95_ID W17LU95_ID true false false 11 Double 0 11 ,First,#,water_LULC,W17LU95_ID,-1,-1;IS1_12__19 IS1_12__19 true false false 4 Short 0 4 ,First,#,water_LULC,IS1_12__19,-1,-1;W10LU95_ W10LU95_ true false false 11 Double 0 11 ,First,#,water_LULC,W10LU95_,-1,-1;W10LU95_ID W10LU95_ID true false false 11 Double 0 11 ,First,#,water_LULC,W10LU95_ID,-1,-1;IS1_12__20 IS1_12__20 true false false 4 Short 0 4 ,First,#,water_LULC,IS1_12__20,-1,-1;W12LU95_ W12LU95_ true false false 11 Double 0 11 ,First,#,water_LULC,W12LU95_,-1,-1;W12LU95_ID W12LU95_ID true false false 11 Double 0 11 ,First,#,water_LULC,W12LU95_ID,-1,-1;IS1_12__21 IS1_12__21 true false false 4 Short 0 4 ,First,#,water_LULC,IS1_12__21,-1,-1;W14LU95_ W14LU95_ true false false 11 Double 0 11 ,First,#,water_LULC,W14LU95_,-1,-1;W14LU95_ID W14LU95_ID true false false 11 Double 0 11 ,First,#,water_LULC,W14LU95_ID,-1,-1;IS1_12__22 IS1_12__22 true false false 4 Short 0 4 ,First,#,water_LULC,IS1_12__22,-1,-1;W08LU95_ W08LU95_ true false false 11 Double 0 11 ,First,#,water_LULC,W08LU95_,-1,-1;W08LU95_ID W08LU95_ID true false false 11 Double 0 11 ,First,#,water_LULC,W08LU95_ID,-1,-1;IS1_12__23 IS1_12__23 true false false 4 Short 0 4 ,First,#,water_LULC,IS1_12__23,-1,-1;W19LU95_ W19LU95_ true false false 11 Double 0 11 ,First,#,water_LULC,W19LU95_,-1,-1;W19LU95_ID W19LU95_ID true false false 11 Double 0 11 ,First,#,water_LULC,W19LU95_ID,-1,-1;IS1_12__24 IS1_12__24 true false false 4 Short 0 4 ,First,#,water_LULC,IS1_12__24,-1,-1;W06LU95_ W06LU95_ true false false 11 Double 0 11 ,First,#,water_LULC,W06LU95_,-1,-1;W06LU95_ID W06LU95_ID true false false 11 Double 0 11 ,First,#,water_LULC,W06LU95_ID,-1,-1;IS1_12__25 IS1_12__25 true false false 4 Short 0 4 ,First,#,water_LULC,IS1_12__25,-1,-1;W03LU95_ W03LU95_ true false false 11 Double 0 11 ,First,#,water_LULC,W03LU95_,-1,-1;W03LU95_ID W03LU95_ID true false false 11 Double 0 11 ,First,#,water_LULC,W03LU95_ID,-1,-1;IS1_12__26 IS1_12__26 true false false 4 Short 0 4 ,First,#,water_LULC,IS1_12__26,-1,-1;W01LU95_ W01LU95_ true false false 11 Double 0 11 ,First,#,water_LULC,W01LU95_,-1,-1;W01LU95_ID W01LU95_ID true false false 11 Double 0 11 ,First,#,water_LULC,W01LU95_ID,-1,-1;IS1_12__27 IS1_12__27 true false false 4 Short 0 4 ,First,#,water_LULC,IS1_12__27,-1,-1;W02LU95_ W02LU95_ true false false 11 Double 0 11 ,First,#,water_LULC,W02LU95_,-1,-1;W02LU95_ID W02LU95_ID true false false 11 Double 0 11 ,First,#,water_LULC,W02LU95_ID,-1,-1;IS1_12__28 IS1_12__28 true false false 4 Short 0 4 ,First,#,water_LULC,IS1_12__28,-1,-1"</Process></lineage></DataProperties><SyncDate>20100607</SyncDate><SyncTime>12201300</SyncTime><ModDate>20100607</ModDate><ModTime>12201300</ModTime></Esri><idinfo><native Sync="TRUE">Microsoft Windows XP Version 5.1 (Build 2600) Service Pack 3; ESRI ArcCatalog 9.3.0.1770</native><descript><langdata Sync="TRUE">en</langdata><abstract>This file was created in 2006 by combining New York, New Jersey, and Connecticut shapefiles. The original file suffered from overlapping and misalighed polygons. Therefore, the file was modified in 2008 using ArcMap Editor to merge the polygons for a more unified shapefile. </abstract><purpose>The data was created as a regional water shapefile for New York, New Jesery, and Connecticut.</purpose></descript><citation><citeinfo><origin>REQUIRED: The name of an organization or individual that developed the data set.</origin><pubdate>REQUIRED: The date when the data set is published or otherwise made available for release.</pubdate><title Sync="TRUE">water_tristate_2008</title><ftname Sync="TRUE">water_tristate_2008</ftname><geoform Sync="TRUE">vector digital data</geoform><onlink Sync="TRUE">\\Newyork\GIS\New_York_City\Water\water_tristate_2008.shp</onlink></citeinfo></citation><timeperd><current>REQUIRED: The basis on which the time period of content information is determined.</current><timeinfo><sngdate><caldate>REQUIRED: The year (and optionally month, or month and day) for which the data set corresponds to the ground.</caldate></sngdate></timeinfo></timeperd><status><progress>REQUIRED: The state of the data set.</progress><update>REQUIRED: The frequency with which changes and additions are made to the data set after the initial data set is completed.</update></status><spdom><bounding><westbc Sync="TRUE">-80.052390</westbc><eastbc Sync="TRUE">-71.714717</eastbc><northbc Sync="TRUE">45.033548</northbc><southbc Sync="TRUE">38.683503</southbc></bounding><lboundng><leftbc Sync="TRUE">-895969.095555</leftbc><rightbc Sync="TRUE">1268170.234553</rightbc><bottombc Sync="TRUE">-210640.668150</bottombc><topbc Sync="TRUE">2031646.180335</topbc></lboundng></spdom><keywords><theme><themekt>REQUIRED: Reference to a formally registered thesaurus or a similar authoritative source of theme keywords.</themekt><themekey>water</themekey></theme></keywords><accconst>None</accconst><useconst>None</useconst><natvform Sync="TRUE">Shapefile</natvform></idinfo><dataIdInfo><envirDesc Sync="TRUE">Microsoft Windows XP Version 5.1 (Build 2600) Service Pack 3; ESRI ArcCatalog 9.3.0.1770</envirDesc><dataLang><languageCode Sync="TRUE" value="en"></languageCode></dataLang><idCitation><resTitle Sync="TRUE">water_tristate_2008</resTitle><presForm><PresFormCd Sync="TRUE" value="005"></PresFormCd></presForm></idCitation><spatRpType><SpatRepTypCd Sync="TRUE" value="001"></SpatRepTypCd></spatRpType><dataExt><geoEle><GeoBndBox esriExtentType="native"><westBL Sync="TRUE">-895969.095555</westBL><eastBL Sync="TRUE">1268170.234553</eastBL><northBL Sync="TRUE">2031646.180335</northBL><southBL Sync="TRUE">-210640.66815</southBL><exTypeCode Sync="TRUE">1</exTypeCode></GeoBndBox></geoEle></dataExt><geoBox esriExtentType="decdegrees"><westBL Sync="TRUE">-80.05239</westBL><eastBL Sync="TRUE">-71.714717</eastBL><northBL Sync="TRUE">45.033548</northBL><southBL Sync="TRUE">38.683503</southBL><exTypeCode Sync="TRUE">1</exTypeCode></geoBox></dataIdInfo><metainfo><langmeta Sync="TRUE">en</langmeta><metstdn Sync="TRUE">FGDC Content Standards for Digital Geospatial Metadata</metstdn><metstdv Sync="TRUE">FGDC-STD-001-1998</metstdv><mettc Sync="TRUE">local time</mettc><metc><cntinfo><cntorgp><cntper>REQUIRED: The person responsible for the metadata information.</cntper><cntorg>REQUIRED: The organization responsible for the metadata information.</cntorg></cntorgp><cntaddr><addrtype>REQUIRED: The mailing and/or physical address for the organization or individual.</addrtype><city>REQUIRED: The city of the address.</city><state>REQUIRED: The state or province of the address.</state><postal>REQUIRED: The ZIP or other postal code of the address.</postal></cntaddr><cntvoice>REQUIRED: The telephone number by which individuals can speak to the organization or individual.</cntvoice></cntinfo></metc><metd Sync="TRUE">20100607</metd><metextns><onlink Sync="TRUE">http://www.esri.com/metadata/esriprof80.html</onlink><metprof Sync="TRUE">ESRI Metadata Profile</metprof></metextns></metainfo><mdLang><languageCode Sync="TRUE" value="en"></languageCode></mdLang><mdStanName Sync="TRUE">ISO 19115 Geographic Information - Metadata</mdStanName><mdStanVer Sync="TRUE">DIS_ESRI1.0</mdStanVer><mdChar><CharSetCd Sync="TRUE" value="004"></CharSetCd></mdChar><mdHrLv><ScopeCd Sync="TRUE" value="005"></ScopeCd></mdHrLv><mdHrLvName Sync="TRUE">dataset</mdHrLvName><distinfo><resdesc Sync="TRUE">Downloadable Data</resdesc><stdorder><digform><digtinfo><transize Sync="TRUE">81.936</transize><dssize Sync="TRUE">81.936</dssize></digtinfo></digform></stdorder></distinfo><distInfo><distributor><distorTran><onLineSrc><orDesc Sync="TRUE">002</orDesc><linkage Sync="TRUE">file://\\Newyork\GIS\New_York_City\Water\water_tristate_2008.shp</linkage><protocol Sync="TRUE">Local Area Network</protocol></onLineSrc><transSize Sync="TRUE">81.936</transSize></distorTran><distorFormat><formatName Sync="TRUE">Shapefile</formatName></distorFormat></distributor></distInfo><spdoinfo><direct Sync="TRUE">Vector</direct><ptvctinf><esriterm Name="water_tristate_2008"><efeatyp Sync="TRUE">Simple</efeatyp><efeageom Sync="TRUE">Polygon</efeageom><esritopo Sync="TRUE">FALSE</esritopo><efeacnt Sync="TRUE">89243</efeacnt><spindex Sync="TRUE">TRUE</spindex><linrefer Sync="TRUE">FALSE</linrefer></esriterm><sdtsterm Name="water_tristate_2008"><sdtstype Sync="TRUE">G-polygon</sdtstype><ptvctcnt Sync="TRUE">89243</ptvctcnt></sdtsterm></ptvctinf></spdoinfo><spref><horizsys><cordsysn><geogcsn Sync="TRUE">GCS_North_American_1983</geogcsn><projcsn Sync="TRUE">NAD_1983_StatePlane_Connecticut_FIPS_0600_Feet</projcsn></cordsysn><planar><planci><plance Sync="TRUE">coordinate pair</plance><plandu Sync="TRUE">survey feet</plandu><coordrep><absres Sync="TRUE">0.000000</absres><ordres Sync="TRUE">0.000000</ordres></coordrep></planci><mapproj><mapprojn Sync="TRUE">Lambert Conformal Conic</mapprojn><lambertc><stdparll Sync="TRUE">41.200000</stdparll><stdparll Sync="TRUE">41.866667</stdparll><longcm Sync="TRUE">-72.750000</longcm><latprjo Sync="TRUE">40.833333</latprjo><feast Sync="TRUE">999999.999996</feast><fnorth Sync="TRUE">499999.999998</fnorth></lambertc></mapproj></planar><geodetic><horizdn Sync="TRUE">North American Datum of 1983</horizdn><ellips Sync="TRUE">Geodetic Reference System 80</ellips><semiaxis Sync="TRUE">6378137.000000</semiaxis><denflat Sync="TRUE">298.257222</denflat></geodetic></horizsys></spref><refSysInfo><RefSystem><refSysID><identCode Sync="TRUE">NAD_1983_StatePlane_Connecticut_FIPS_0600_Feet</identCode></refSysID></RefSystem></refSysInfo><spatRepInfo><VectSpatRep><topLvl><TopoLevCd Sync="TRUE" value="001"></TopoLevCd></topLvl><geometObjs Name="water_tristate_2008"><geoObjTyp><GeoObjTypCd Sync="TRUE" value="001"></GeoObjTypCd></geoObjTyp><geoObjCnt Sync="TRUE">89243</geoObjCnt></geometObjs></VectSpatRep></spatRepInfo><eainfo><detailed Name="water_tristate_2008"><enttyp><enttypl Sync="TRUE">water_tristate_2008</enttypl><enttypt Sync="TRUE">Feature Class</enttypt><enttypc Sync="TRUE">89243</enttypc></enttyp><attr><attrlabl Sync="TRUE">FID</attrlabl><attalias Sync="TRUE">FID</attalias><attrtype Sync="TRUE">OID</attrtype><attwidth Sync="TRUE">4</attwidth><atprecis Sync="TRUE">0</atprecis><attscale Sync="TRUE">0</attscale><attrdef Sync="TRUE">Internal feature number.</attrdef><attrdefs Sync="TRUE">ESRI</attrdefs><attrdomv><udom Sync="TRUE">Sequential unique whole numbers that are automatically generated.</udom></attrdomv></attr><attr><attrlabl Sync="TRUE">Shape</attrlabl><attalias Sync="TRUE">Shape</attalias><attrtype Sync="TRUE">Geometry</attrtype><attwidth Sync="TRUE">0</attwidth><atprecis Sync="TRUE">0</atprecis><attscale Sync="TRUE">0</attscale><attrdef Sync="TRUE">Feature geometry.</attrdef><attrdefs Sync="TRUE">ESRI</attrdefs><attrdomv><udom Sync="TRUE">Coordinates defining the features.</udom></attrdomv></attr><attr><attrlabl Sync="TRUE">HYPOLY_COD</attrlabl><attalias Sync="TRUE">HYPOLY_COD</attalias><attrtype Sync="TRUE">Number</attrtype><attwidth Sync="TRUE">10</attwidth></attr><attr><attrlabl Sync="TRUE">HYDRO_POLY</attrlabl><attalias Sync="TRUE">HYDRO_POLY</attalias><attrtype Sync="TRUE">String</attrtype><attwidth Sync="TRUE">50</attwidth></attr><attr><attrlabl Sync="TRUE">AV_LEGEND</attrlabl><attalias Sync="TRUE">AV_LEGEND</attalias><attrtype Sync="TRUE">String</attrtype><attwidth Sync="TRUE">20</attwidth></attr><attr><attrlabl Sync="TRUE">IMS_LEGEND</attrlabl><attalias Sync="TRUE">IMS_LEGEND</attalias><attrtype Sync="TRUE">String</attrtype><attwidth Sync="TRUE">20</attwidth></attr><attr><attrlabl Sync="TRUE">COASTP_COD</attrlabl><attalias Sync="TRUE">COASTP_COD</attalias><attrtype Sync="TRUE">Number</attrtype><attwidth Sync="TRUE">1</attwidth></attr><attr><attrlabl Sync="TRUE">COAST_POLY</attrlabl><attalias Sync="TRUE">COAST_POLY</attalias><attrtype Sync="TRUE">String</attrtype><attwidth Sync="TRUE">30</attwidth></attr><attr><attrlabl Sync="TRUE">NAMEDP_COD</attrlabl><attalias Sync="TRUE">NAMEDP_COD</attalias><attrtype Sync="TRUE">Number</attrtype><attwidth Sync="TRUE">1</attwidth></attr><attr><attrlabl Sync="TRUE">NAMED_POLY</attrlabl><attalias Sync="TRUE">NAMED_POLY</attalias><attrtype Sync="TRUE">String</attrtype><attwidth Sync="TRUE">40</attwidth></attr><attr><attrlabl Sync="TRUE">SCALELEVEL</attrlabl><attalias Sync="TRUE">SCALELEVEL</attalias><attrtype Sync="TRUE">Number</attrtype><attwidth Sync="TRUE">1</attwidth></attr><attr><attrlabl Sync="TRUE">STREAM_NO</attrlabl><attalias Sync="TRUE">STREAM_NO</attalias><attrtype Sync="TRUE">Number</attrtype><attwidth Sync="TRUE">5</attwidth></attr><attr><attrlabl Sync="TRUE">STREAM</attrlabl><attalias Sync="TRUE">STREAM</attalias><attrtype Sync="TRUE">String</attrtype><attwidth Sync="TRUE">40</attwidth></attr><attr><attrlabl Sync="TRUE">LAKE_NO</attrlabl><attalias Sync="TRUE">LAKE_NO</attalias><attrtype Sync="TRUE">Number</attrtype><attwidth Sync="TRUE">5</attwidth></attr><attr><attrlabl Sync="TRUE">LAKE</attrlabl><attalias Sync="TRUE">LAKE</attalias><attrtype Sync="TRUE">String</attrtype><attwidth Sync="TRUE">40</attwidth></attr><attr><attrlabl Sync="TRUE">BAY_NO</attrlabl><attalias Sync="TRUE">BAY_NO</attalias><attrtype Sync="TRUE">Number</attrtype><attwidth Sync="TRUE">5</attwidth></attr><attr><attrlabl Sync="TRUE">BAY</attrlabl><attalias Sync="TRUE">BAY</attalias><attrtype Sync="TRUE">String</attrtype><attwidth Sync="TRUE">40</attwidth></attr><attr><attrlabl Sync="TRUE">HARBOR_NO</attrlabl><attalias Sync="TRUE">HARBOR_NO</attalias><attrtype Sync="TRUE">Number</attrtype><attwidth Sync="TRUE">5</attwidth></attr><attr><attrlabl Sync="TRUE">HARBOR</attrlabl><attalias Sync="TRUE">HARBOR</attalias><attrtype Sync="TRUE">String</attrtype><attwidth Sync="TRUE">40</attwidth></attr><attr><attrlabl Sync="TRUE">SOUND_NO</attrlabl><attalias Sync="TRUE">SOUND_NO</attalias><attrtype Sync="TRUE">Number</attrtype><attwidth Sync="TRUE">5</attwidth></attr><attr><attrlabl Sync="TRUE">SOUND</attrlabl><attalias Sync="TRUE">SOUND</attalias><attrtype Sync="TRUE">String</attrtype><attwidth Sync="TRUE">30</attwidth></attr><attr><attrlabl Sync="TRUE">ACREAGE</attrlabl><attalias Sync="TRUE">ACREAGE</attalias><attrtype Sync="TRUE">Number</attrtype><attwidth Sync="TRUE">13</attwidth><atnumdec Sync="TRUE">11</atnumdec></attr><attr><attrlabl Sync="TRUE">NAME</attrlabl><attalias Sync="TRUE">NAME</attalias><attrtype Sync="TRUE">String</attrtype><attwidth Sync="TRUE">40</attwidth></attr><attr><attrlabl Sync="TRUE">FCC</attrlabl><attalias Sync="TRUE">FCC</attalias><attrtype Sync="TRUE">String</attrtype><attwidth Sync="TRUE">3</attwidth></attr><attr><attrlabl Sync="TRUE">BUS_FID_Le</attrlabl><attalias Sync="TRUE">BUS_FID_Le</attalias><attrtype Sync="TRUE">Number</attrtype><attwidth Sync="TRUE">19</attwidth><atnumdec Sync="TRUE">11</atnumdec></attr><attr><attrlabl Sync="TRUE">BUS_FID_Ar</attrlabl><attalias Sync="TRUE">BUS_FID_Ar</attalias><attrtype Sync="TRUE">Number</attrtype><attwidth Sync="TRUE">19</attwidth><atnumdec Sync="TRUE">11</atnumdec></attr><attr><attrlabl Sync="TRUE">AREA</attrlabl><attalias Sync="TRUE">AREA</attalias><attrtype Sync="TRUE">Number</attrtype><attwidth Sync="TRUE">19</attwidth><atnumdec Sync="TRUE">5</atnumdec></attr><attr><attrlabl Sync="TRUE">PERIMETER</attrlabl><attalias Sync="TRUE">PERIMETER</attalias><attrtype Sync="TRUE">Number</attrtype><attwidth Sync="TRUE">19</attwidth><atnumdec Sync="TRUE">5</atnumdec></attr><attr><attrlabl Sync="TRUE">W07LU95_</attrlabl><attalias Sync="TRUE">W07LU95_</attalias><attrtype Sync="TRUE">Number</attrtype><attwidth Sync="TRUE">11</attwidth></attr><attr><attrlabl Sync="TRUE">W07LU95_ID</attrlabl><attalias Sync="TRUE">W07LU95_ID</attalias><attrtype Sync="TRUE">Number</attrtype><attwidth Sync="TRUE">11</attwidth></attr><attr><attrlabl Sync="TRUE">STATUS</attrlabl><attalias Sync="TRUE">STATUS</attalias><attrtype Sync="TRUE">String</attrtype><attwidth Sync="TRUE">16</attwidth></attr><attr><attrlabl Sync="TRUE">APPROVAL</attrlabl><attalias Sync="TRUE">APPROVAL</attalias><attrtype Sync="TRUE">String</attrtype><attwidth Sync="TRUE">8</attwidth></attr><attr><attrlabl Sync="TRUE">ACRES</attrlabl><attalias Sync="TRUE">ACRES</attalias><attrtype Sync="TRUE">Number</attrtype><attwidth Sync="TRUE">15</attwidth><atnumdec Sync="TRUE">3</atnumdec></attr><attr><attrlabl Sync="TRUE">LU95</attrlabl><attalias Sync="TRUE">LU95</attalias><attrtype Sync="TRUE">Number</attrtype><attwidth Sync="TRUE">4</attwidth></attr><attr><attrlabl Sync="TRUE">LABEL95</attrlabl><attalias Sync="TRUE">LABEL95</attalias><attrtype Sync="TRUE">String</attrtype><attwidth Sync="TRUE">65</attwidth></attr><attr><attrlabl Sync="TRUE">TYPE95</attrlabl><attalias Sync="TRUE">TYPE95</attalias><attrtype Sync="TRUE">String</attrtype><attwidth Sync="TRUE">15</attwidth></attr><attr><attrlabl Sync="TRUE">IS_</attrlabl><attalias Sync="TRUE">IS_</attalias><attrtype Sync="TRUE">Number</attrtype><attwidth Sync="TRUE">4</attwidth></attr><attr><attrlabl Sync="TRUE">ISACRES</attrlabl><attalias Sync="TRUE">ISACRES</attalias><attrtype Sync="TRUE">Number</attrtype><attwidth Sync="TRUE">15</attwidth><atnumdec Sync="TRUE">3</atnumdec></attr><attr><attrlabl Sync="TRUE">CHANGE86</attrlabl><attalias Sync="TRUE">CHANGE86</attalias><attrtype Sync="TRUE">Number</attrtype><attwidth Sync="TRUE">2</attwidth></attr><attr><attrlabl Sync="TRUE">LU86</attrlabl><attalias Sync="TRUE">LU86</attalias><attrtype Sync="TRUE">Number</attrtype><attwidth Sync="TRUE">4</attwidth></attr><attr><attrlabl Sync="TRUE">LABEL86</attrlabl><attalias Sync="TRUE">LABEL86</attalias><attrtype Sync="TRUE">String</attrtype><attwidth Sync="TRUE">65</attwidth></attr><attr><attrlabl Sync="TRUE">TYPE86</attrlabl><attalias Sync="TRUE">TYPE86</attalias><attrtype Sync="TRUE">String</attrtype><attwidth Sync="TRUE">15</attwidth></attr><attr><attrlabl Sync="TRUE">CLASS</attrlabl><attalias Sync="TRUE">CLASS</attalias><attrtype Sync="TRUE">Number</attrtype><attwidth Sync="TRUE">6</attwidth></attr><attr><attrlabl Sync="TRUE">COWARDIN</attrlabl><attalias Sync="TRUE">COWARDIN</attalias><attrtype Sync="TRUE">String</attrtype><attwidth Sync="TRUE">14</attwidth></attr><attr><attrlabl Sync="TRUE">W20LU95_</attrlabl><attalias Sync="TRUE">W20LU95_</attalias><attrtype Sync="TRUE">Number</attrtype><attwidth Sync="TRUE">11</attwidth></attr><attr><attrlabl Sync="TRUE">W20LU95_ID</attrlabl><attalias Sync="TRUE">W20LU95_ID</attalias><attrtype Sync="TRUE">Number</attrtype><attwidth Sync="TRUE">11</attwidth></attr><attr><attrlabl Sync="TRUE">IS1</attrlabl><attalias Sync="TRUE">IS1</attalias><attrtype Sync="TRUE">Number</attrtype><attwidth Sync="TRUE">4</attwidth></attr><attr><attrlabl Sync="TRUE">W13LU95_</attrlabl><attalias Sync="TRUE">W13LU95_</attalias><attrtype Sync="TRUE">Number</attrtype><attwidth Sync="TRUE">11</attwidth></attr><attr><attrlabl Sync="TRUE">W13LU95_ID</attrlabl><attalias Sync="TRUE">W13LU95_ID</attalias><attrtype Sync="TRUE">Number</attrtype><attwidth Sync="TRUE">11</attwidth></attr><attr><attrlabl Sync="TRUE">IS1_1</attrlabl><attalias Sync="TRUE">IS1_1</attalias><attrtype Sync="TRUE">Number</attrtype><attwidth Sync="TRUE">4</attwidth></attr><attr><attrlabl Sync="TRUE">W16LU95_</attrlabl><attalias Sync="TRUE">W16LU95_</attalias><attrtype Sync="TRUE">Number</attrtype><attwidth Sync="TRUE">11</attwidth></attr><attr><attrlabl Sync="TRUE">W16LU95_ID</attrlabl><attalias Sync="TRUE">W16LU95_ID</attalias><attrtype Sync="TRUE">Number</attrtype><attwidth Sync="TRUE">11</attwidth></attr><attr><attrlabl Sync="TRUE">IS1_12</attrlabl><attalias Sync="TRUE">IS1_12</attalias><attrtype Sync="TRUE">Number</attrtype><attwidth Sync="TRUE">4</attwidth></attr><attr><attrlabl Sync="TRUE">W11LU95_</attrlabl><attalias Sync="TRUE">W11LU95_</attalias><attrtype Sync="TRUE">Number</attrtype><attwidth Sync="TRUE">11</attwidth></attr><attr><attrlabl Sync="TRUE">W11LU95_ID</attrlabl><attalias Sync="TRUE">W11LU95_ID</attalias><attrtype Sync="TRUE">Number</attrtype><attwidth Sync="TRUE">11</attwidth></attr><attr><attrlabl Sync="TRUE">IS1_12_13</attrlabl><attalias Sync="TRUE">IS1_12_13</attalias><attrtype Sync="TRUE">Number</attrtype><attwidth Sync="TRUE">4</attwidth></attr><attr><attrlabl Sync="TRUE">W15LU95_</attrlabl><attalias Sync="TRUE">W15LU95_</attalias><attrtype Sync="TRUE">Number</attrtype><attwidth Sync="TRUE">11</attwidth></attr><attr><attrlabl Sync="TRUE">W15LU95_ID</attrlabl><attalias Sync="TRUE">W15LU95_ID</attalias><attrtype Sync="TRUE">Number</attrtype><attwidth Sync="TRUE">11</attwidth></attr><attr><attrlabl Sync="TRUE">IS1_12__14</attrlabl><attalias Sync="TRUE">IS1_12__14</attalias><attrtype Sync="TRUE">Number</attrtype><attwidth Sync="TRUE">4</attwidth></attr><attr><attrlabl Sync="TRUE">W05LU95_</attrlabl><attalias Sync="TRUE">W05LU95_</attalias><attrtype Sync="TRUE">Number</attrtype><attwidth Sync="TRUE">11</attwidth></attr><attr><attrlabl Sync="TRUE">W05LU95_ID</attrlabl><attalias Sync="TRUE">W05LU95_ID</attalias><attrtype Sync="TRUE">Number</attrtype><attwidth Sync="TRUE">11</attwidth></attr><attr><attrlabl Sync="TRUE">IS1_12__15</attrlabl><attalias Sync="TRUE">IS1_12__15</attalias><attrtype Sync="TRUE">Number</attrtype><attwidth Sync="TRUE">4</attwidth></attr><attr><attrlabl Sync="TRUE">W18LU95_</attrlabl><attalias Sync="TRUE">W18LU95_</attalias><attrtype Sync="TRUE">Number</attrtype><attwidth Sync="TRUE">11</attwidth></attr><attr><attrlabl Sync="TRUE">W18LU95_ID</attrlabl><attalias Sync="TRUE">W18LU95_ID</attalias><attrtype Sync="TRUE">Number</attrtype><attwidth Sync="TRUE">11</attwidth></attr><attr><attrlabl Sync="TRUE">IS1_12__16</attrlabl><attalias Sync="TRUE">IS1_12__16</attalias><attrtype Sync="TRUE">Number</attrtype><attwidth Sync="TRUE">4</attwidth></attr><attr><attrlabl Sync="TRUE">W04LU95_</attrlabl><attalias Sync="TRUE">W04LU95_</attalias><attrtype Sync="TRUE">Number</attrtype><attwidth Sync="TRUE">11</attwidth></attr><attr><attrlabl Sync="TRUE">W04LU95_ID</attrlabl><attalias Sync="TRUE">W04LU95_ID</attalias><attrtype Sync="TRUE">Number</attrtype><attwidth Sync="TRUE">11</attwidth></attr><attr><attrlabl Sync="TRUE">IS1_12__17</attrlabl><attalias Sync="TRUE">IS1_12__17</attalias><attrtype Sync="TRUE">Number</attrtype><attwidth Sync="TRUE">4</attwidth></attr><attr><attrlabl Sync="TRUE">W09LU95_</attrlabl><attalias Sync="TRUE">W09LU95_</attalias><attrtype Sync="TRUE">Number</attrtype><attwidth Sync="TRUE">11</attwidth></attr><attr><attrlabl Sync="TRUE">W09LU95_ID</attrlabl><attalias Sync="TRUE">W09LU95_ID</attalias><attrtype Sync="TRUE">Number</attrtype><attwidth Sync="TRUE">11</attwidth></attr><attr><attrlabl Sync="TRUE">IS1_12__18</attrlabl><attalias Sync="TRUE">IS1_12__18</attalias><attrtype Sync="TRUE">Number</attrtype><attwidth Sync="TRUE">4</attwidth></attr><attr><attrlabl Sync="TRUE">W17LU95_</attrlabl><attalias Sync="TRUE">W17LU95_</attalias><attrtype Sync="TRUE">Number</attrtype><attwidth Sync="TRUE">11</attwidth></attr><attr><attrlabl Sync="TRUE">W17LU95_ID</attrlabl><attalias Sync="TRUE">W17LU95_ID</attalias><attrtype Sync="TRUE">Number</attrtype><attwidth Sync="TRUE">11</attwidth></attr><attr><attrlabl Sync="TRUE">IS1_12__19</attrlabl><attalias Sync="TRUE">IS1_12__19</attalias><attrtype Sync="TRUE">Number</attrtype><attwidth Sync="TRUE">4</attwidth></attr><attr><attrlabl Sync="TRUE">W10LU95_</attrlabl><attalias Sync="TRUE">W10LU95_</attalias><attrtype Sync="TRUE">Number</attrtype><attwidth Sync="TRUE">11</attwidth></attr><attr><attrlabl Sync="TRUE">W10LU95_ID</attrlabl><attalias Sync="TRUE">W10LU95_ID</attalias><attrtype Sync="TRUE">Number</attrtype><attwidth Sync="TRUE">11</attwidth></attr><attr><attrlabl Sync="TRUE">IS1_12__20</attrlabl><attalias Sync="TRUE">IS1_12__20</attalias><attrtype Sync="TRUE">Number</attrtype><attwidth Sync="TRUE">4</attwidth></attr><attr><attrlabl Sync="TRUE">W12LU95_</attrlabl><attalias Sync="TRUE">W12LU95_</attalias><attrtype Sync="TRUE">Number</attrtype><attwidth Sync="TRUE">11</attwidth></attr><attr><attrlabl Sync="TRUE">W12LU95_ID</attrlabl><attalias Sync="TRUE">W12LU95_ID</attalias><attrtype Sync="TRUE">Number</attrtype><attwidth Sync="TRUE">11</attwidth></attr><attr><attrlabl Sync="TRUE">IS1_12__21</attrlabl><attalias Sync="TRUE">IS1_12__21</attalias><attrtype Sync="TRUE">Number</attrtype><attwidth Sync="TRUE">4</attwidth></attr><attr><attrlabl Sync="TRUE">W14LU95_</attrlabl><attalias Sync="TRUE">W14LU95_</attalias><attrtype Sync="TRUE">Number</attrtype><attwidth Sync="TRUE">11</attwidth></attr><attr><attrlabl Sync="TRUE">W14LU95_ID</attrlabl><attalias Sync="TRUE">W14LU95_ID</attalias><attrtype Sync="TRUE">Number</attrtype><attwidth Sync="TRUE">11</attwidth></attr><attr><attrlabl Sync="TRUE">IS1_12__22</attrlabl><attalias Sync="TRUE">IS1_12__22</attalias><attrtype Sync="TRUE">Number</attrtype><attwidth Sync="TRUE">4</attwidth></attr><attr><attrlabl Sync="TRUE">W08LU95_</attrlabl><attalias Sync="TRUE">W08LU95_</attalias><attrtype Sync="TRUE">Number</attrtype><attwidth Sync="TRUE">11</attwidth></attr><attr><attrlabl Sync="TRUE">W08LU95_ID</attrlabl><attalias Sync="TRUE">W08LU95_ID</attalias><attrtype Sync="TRUE">Number</attrtype><attwidth Sync="TRUE">11</attwidth></attr><attr><attrlabl Sync="TRUE">IS1_12__23</attrlabl><attalias Sync="TRUE">IS1_12__23</attalias><attrtype Sync="TRUE">Number</attrtype><attwidth Sync="TRUE">4</attwidth></attr><attr><attrlabl Sync="TRUE">W19LU95_</attrlabl><attalias Sync="TRUE">W19LU95_</attalias><attrtype Sync="TRUE">Number</attrtype><attwidth Sync="TRUE">11</attwidth></attr><attr><attrlabl Sync="TRUE">W19LU95_ID</attrlabl><attalias Sync="TRUE">W19LU95_ID</attalias><attrtype Sync="TRUE">Number</attrtype><attwidth Sync="TRUE">11</attwidth></attr><attr><attrlabl Sync="TRUE">IS1_12__24</attrlabl><attalias Sync="TRUE">IS1_12__24</attalias><attrtype Sync="TRUE">Number</attrtype><attwidth Sync="TRUE">4</attwidth></attr><attr><attrlabl Sync="TRUE">W06LU95_</attrlabl><attalias Sync="TRUE">W06LU95_</attalias><attrtype Sync="TRUE">Number</attrtype><attwidth Sync="TRUE">11</attwidth></attr><attr><attrlabl Sync="TRUE">W06LU95_ID</attrlabl><attalias Sync="TRUE">W06LU95_ID</attalias><attrtype Sync="TRUE">Number</attrtype><attwidth Sync="TRUE">11</attwidth></attr><attr><attrlabl Sync="TRUE">IS1_12__25</attrlabl><attalias Sync="TRUE">IS1_12__25</attalias><attrtype Sync="TRUE">Number</attrtype><attwidth Sync="TRUE">4</attwidth></attr><attr><attrlabl Sync="TRUE">W03LU95_</attrlabl><attalias Sync="TRUE">W03LU95_</attalias><attrtype Sync="TRUE">Number</attrtype><attwidth Sync="TRUE">11</attwidth></attr><attr><attrlabl Sync="TRUE">W03LU95_ID</attrlabl><attalias Sync="TRUE">W03LU95_ID</attalias><attrtype Sync="TRUE">Number</attrtype><attwidth Sync="TRUE">11</attwidth></attr><attr><attrlabl Sync="TRUE">IS1_12__26</attrlabl><attalias Sync="TRUE">IS1_12__26</attalias><attrtype Sync="TRUE">Number</attrtype><attwidth Sync="TRUE">4</attwidth></attr><attr><attrlabl Sync="TRUE">W01LU95_</attrlabl><attalias Sync="TRUE">W01LU95_</attalias><attrtype Sync="TRUE">Number</attrtype><attwidth Sync="TRUE">11</attwidth></attr><attr><attrlabl Sync="TRUE">W01LU95_ID</attrlabl><attalias Sync="TRUE">W01LU95_ID</attalias><attrtype Sync="TRUE">Number</attrtype><attwidth Sync="TRUE">11</attwidth></attr><attr><attrlabl Sync="TRUE">IS1_12__27</attrlabl><attalias Sync="TRUE">IS1_12__27</attalias><attrtype Sync="TRUE">Number</attrtype><attwidth Sync="TRUE">4</attwidth></attr><attr><attrlabl Sync="TRUE">W02LU95_</attrlabl><attalias Sync="TRUE">W02LU95_</attalias><attrtype Sync="TRUE">Number</attrtype><attwidth Sync="TRUE">11</attwidth></attr><attr><attrlabl Sync="TRUE">W02LU95_ID</attrlabl><attalias Sync="TRUE">W02LU95_ID</attalias><attrtype Sync="TRUE">Number</attrtype><attwidth Sync="TRUE">11</attwidth></attr><attr><attrlabl Sync="TRUE">IS1_12__28</attrlabl><attalias Sync="TRUE">IS1_12__28</attalias><attrtype Sync="TRUE">Number</attrtype><attwidth Sync="TRUE">4</attwidth></attr><attr><attrlabl Sync="TRUE">dom</attrlabl><attalias Sync="TRUE">dom</attalias><attrtype Sync="TRUE">Number</attrtype><attwidth Sync="TRUE">18</attwidth></attr></detailed></eainfo><mdDateSt Sync="TRUE">20100607</mdDateSt></metadata>
